README.rst
setup.py
buildbot_status_logentries.egg-info/PKG-INFO
buildbot_status_logentries.egg-info/SOURCES.txt
buildbot_status_logentries.egg-info/dependency_links.txt
buildbot_status_logentries.egg-info/entry_points.txt
buildbot_status_logentries.egg-info/requires.txt
buildbot_status_logentries.egg-info/top_level.txt
logentries/__init__.py