Metadata-Version: 1.1
Name: buildbot-status-logentries
Version: 0.0.3
Summary: A Logentries status plugin for buildbot
Home-page: http://www.logentries.com/
Author: Jimmy Tang
Author-email: jimmy_tang@rapid7.com
License: MIT
Keywords: buildbot status logentries
Platform: UNKNOWN
Classifier: Development Status :: 3 - Alpha
Classifier: Intended Audience :: Developers
Classifier: Topic :: Software Development :: Build Tools
Classifier: License :: OSI Approved :: MIT License
Classifier: Programming Language :: Python :: 2.7
